logictree.py
logictree-1.1.3.dist-info/licenses/LICENSE
logictree-1.1.3.dist-info/METADATA
logictree-1.1.3.dist-info/WHEEL
logictree-1.1.3.dist-info/top_level.txt
logictree-1.1.3.dist-info/RECORD
