Metadata-Version: 2.4
Name: logictree
Version: 1.1.3
Summary: Powerful Ligic Tree operations.
Author-email: V Stone <vstone@126.com>
Project-URL: Homepage, https://gitee.com/stone10000/stoneutils/
Project-URL: Issue Tracker, https://gitee.com/stone10000/stoneutils/issues
Classifier: Programming Language :: Python :: 3
Classifier: License :: OSI Approved :: MIT License
Classifier: Operating System :: OS Independent
Requires-Python: >=3.8
License-File: LICENSE
Dynamic: license-file
